kpi/__init__.py
kpi/app/__init__.py
kpi/app/runner.py
kpi/app/detector/__init__.py
kpi/app/detector/detector.py
kpi/app/profiler/__init__.py
kpi/app/profiler/profiler.py
kpi/test/__init__.py
kpi/test/detector/__init__.py
kpi/test/detector/detector_test.py
kpi/test/profiler/__init__.py
kpi/test/profiler/profiler_test.py
kpi_data_drift_detector-1.0.1.dist-info/METADATA
kpi_data_drift_detector-1.0.1.dist-info/WHEEL
kpi_data_drift_detector-1.0.1.dist-info/top_level.txt
kpi_data_drift_detector-1.0.1.dist-info/RECORD
