Metadata-Version: 2.4
Name: kpi-data-drift-detector
Version: 1.0.1
Author: Daria Yurchenko
Requires-Python: >=3.6
Requires-Dist: pandas>=1.5.0
Requires-Dist: scikit-learn>=1.0
Requires-Dist: pytest>=7.0.0
Dynamic: author
Dynamic: requires-dist
Dynamic: requires-python
